{
  "updated_at": "28/04 08:42",
  "value": [
    {
      "league": "Championship",
      "home": "Southampton FC",
      "away": "Ipswich Town FC",
      "kickoff": "28/04 18:45",
      "markets": {
        "over25": 0.7,
        "corners95": 0.59,
        "cards_home": 0.53,
        "cards_away": 0.51,
        "dnb_home": 0.65,
        "xg": 3.06,
        "expected_corners": 11.1
      }
    },
    {
      "league": "UEFA Champions League",
      "home": "Paris Saint-Germain FC",
      "away": "FC Bayern München",
      "kickoff": "28/04 19:00",
      "markets": {
        "over25": 0.63,
        "corners95": 0.59,
        "cards_home": 0.6,
        "cards_away": 0.63,
        "dnb_home": 0.61,
        "xg": 2.68,
        "expected_corners": 12.7
      }
    },
    {
      "league": "Copa Libertadores",
      "home": "Club Libertad Asuncion",
      "away": "CAR Independiente del Valle",
      "kickoff": "28/04 22:00",
      "markets": {
        "over25": 0.7,
        "corners95": 0.67,
        "cards_home": 0.59,
        "cards_away": 0.51,
        "dnb_home": 0.67,
        "xg": 3.04,
        "expected_corners": 12.7
      }
    }
  ],
  "corner": [
    {
      "league": "Copa Libertadores",
      "home": "Club Libertad Asuncion",
      "away": "CAR Independiente del Valle",
      "kickoff": "28/04 22:00",
      "markets": {
        "over25": 0.7,
        "corners95": 0.67,
        "cards_home": 0.59,
        "cards_away": 0.51,
        "dnb_home": 0.67,
        "xg": 3.04,
        "expected_corners": 12.7
      }
    },
    {
      "league": "Copa Libertadores",
      "home": "CA Lanús",
      "away": "LDU de Quito",
      "kickoff": "28/04 22:00",
      "markets": {
        "over25": 0.6,
        "corners95": 0.66,
        "cards_home": 0.6,
        "cards_away": 0.68,
        "dnb_home": 0.6,
        "xg": 2.95,
        "expected_corners": 10.9
      }
    }
  ],
  "hot": []
}