{
  "updated_at": "19/05 11:39",
  "value": [
    {
      "league": "Premier League",
      "home": "AFC Bournemouth",
      "away": "Manchester City FC",
      "kickoff": "19/05 18:30",
      "markets": {
        "over25": 0.69,
        "corners95": 0.58,
        "cards_home": 0.64,
        "cards_away": 0.67,
        "dnb_home": 0.64,
        "xg": 3.27,
        "expected_corners": 9.4
      }
    },
    {
      "league": "Premier League",
      "home": "Chelsea FC",
      "away": "Tottenham Hotspur FC",
      "kickoff": "19/05 19:15",
      "markets": {
        "over25": 0.64,
        "corners95": 0.56,
        "cards_home": 0.55,
        "cards_away": 0.66,
        "dnb_home": 0.74,
        "xg": 2.54,
        "expected_corners": 10.4
      }
    },
    {
      "league": "Copa Libertadores",
      "home": "CA Rosario Central",
      "away": "Universidad Central de Venezuela FC",
      "kickoff": "19/05 22:00",
      "markets": {
        "over25": 0.63,
        "corners95": 0.64,
        "cards_home": 0.59,
        "cards_away": 0.66,
        "dnb_home": 0.57,
        "xg": 2.24,
        "expected_corners": 10.0
      }
    }
  ],
  "corner": [
    {
      "league": "Copa Libertadores",
      "home": "Fluminense FC",
      "away": "Club Bolívar",
      "kickoff": "19/05 22:00",
      "markets": {
        "over25": 0.59,
        "corners95": 0.67,
        "cards_home": 0.56,
        "cards_away": 0.61,
        "dnb_home": 0.63,
        "xg": 3.05,
        "expected_corners": 10.0
      }
    },
    {
      "league": "Copa Libertadores",
      "home": "CA Rosario Central",
      "away": "Universidad Central de Venezuela FC",
      "kickoff": "19/05 22:00",
      "markets": {
        "over25": 0.63,
        "corners95": 0.64,
        "cards_home": 0.59,
        "cards_away": 0.66,
        "dnb_home": 0.57,
        "xg": 2.24,
        "expected_corners": 10.0
      }
    }
  ],
  "hot": [
    {
      "league": "Premier League",
      "home": "Chelsea FC",
      "away": "Tottenham Hotspur FC",
      "kickoff": "19/05 19:15",
      "markets": {
        "over25": 0.64,
        "corners95": 0.56,
        "cards_home": 0.55,
        "cards_away": 0.66,
        "dnb_home": 0.74,
        "xg": 2.54,
        "expected_corners": 10.4
      }
    }
  ]
}