{
  "updated_at": "17/04 06:03",
  "value": [
    {
      "league": "Copa Libertadores",
      "home": "CR Flamengo",
      "away": "CD Independiente Medellín",
      "kickoff": "17/04 00:30",
      "markets": {
        "over25": 0.67,
        "corners95": 0.67,
        "cards_home": 0.61,
        "cards_away": 0.53,
        "dnb_home": 0.68,
        "xg": 2.86,
        "expected_corners": 10.1
      }
    },
    {
      "league": "Bundesliga",
      "home": "FC St. Pauli 1910",
      "away": "1. FC Köln",
      "kickoff": "17/04 18:30",
      "markets": {
        "over25": 0.63,
        "corners95": 0.6,
        "cards_home": 0.55,
        "cards_away": 0.63,
        "dnb_home": 0.63,
        "xg": 3.24,
        "expected_corners": 11.2
      }
    },
    {
      "league": "Championship",
      "home": "Blackburn Rovers FC",
      "away": "Coventry City FC",
      "kickoff": "17/04 19:00",
      "markets": {
        "over25": 0.65,
        "corners95": 0.65,
        "cards_home": 0.66,
        "cards_away": 0.65,
        "dnb_home": 0.57,
        "xg": 2.49,
        "expected_corners": 12.6
      }
    },
    {
      "league": "Primeira Liga",
      "home": "Rio Ave FC",
      "away": "AVS",
      "kickoff": "17/04 19:45",
      "markets": {
        "over25": 0.65,
        "corners95": 0.68,
        "cards_home": 0.65,
        "cards_away": 0.67,
        "dnb_home": 0.71,
        "xg": 3.21,
        "expected_corners": 8.6
      }
    }
  ],
  "corner": [
    {
      "league": "Copa Libertadores",
      "home": "CA Peñarol",
      "away": "CA Platense",
      "kickoff": "17/04 00:30",
      "markets": {
        "over25": 0.6,
        "corners95": 0.64,
        "cards_home": 0.62,
        "cards_away": 0.64,
        "dnb_home": 0.59,
        "xg": 2.54,
        "expected_corners": 9.4
      }
    },
    {
      "league": "Copa Libertadores",
      "home": "CR Flamengo",
      "away": "CD Independiente Medellín",
      "kickoff": "17/04 00:30",
      "markets": {
        "over25": 0.67,
        "corners95": 0.67,
        "cards_home": 0.61,
        "cards_away": 0.53,
        "dnb_home": 0.68,
        "xg": 2.86,
        "expected_corners": 10.1
      }
    },
    {
      "league": "Serie A",
      "home": "US Sassuolo Calcio",
      "away": "Como 1907",
      "kickoff": "17/04 16:30",
      "markets": {
        "over25": 0.62,
        "corners95": 0.63,
        "cards_home": 0.6,
        "cards_away": 0.65,
        "dnb_home": 0.62,
        "xg": 2.75,
        "expected_corners": 9.3
      }
    },
    {
      "league": "Serie A",
      "home": "FC Internazionale Milano",
      "away": "Cagliari Calcio",
      "kickoff": "17/04 18:45",
      "markets": {
        "over25": 0.57,
        "corners95": 0.63,
        "cards_home": 0.52,
        "cards_away": 0.51,
        "dnb_home": 0.7,
        "xg": 3.19,
        "expected_corners": 12.6
      }
    },
    {
      "league": "Ligue 1",
      "home": "Racing Club de Lens",
      "away": "Toulouse FC",
      "kickoff": "17/04 18:45",
      "markets": {
        "over25": 0.55,
        "corners95": 0.64,
        "cards_home": 0.68,
        "cards_away": 0.57,
        "dnb_home": 0.62,
        "xg": 2.36,
        "expected_corners": 10.2
      }
    },
    {
      "league": "Championship",
      "home": "Blackburn Rovers FC",
      "away": "Coventry City FC",
      "kickoff": "17/04 19:00",
      "markets": {
        "over25": 0.65,
        "corners95": 0.65,
        "cards_home": 0.66,
        "cards_away": 0.65,
        "dnb_home": 0.57,
        "xg": 2.49,
        "expected_corners": 12.6
      }
    },
    {
      "league": "Primeira Liga",
      "home": "Rio Ave FC",
      "away": "AVS",
      "kickoff": "17/04 19:45",
      "markets": {
        "over25": 0.65,
        "corners95": 0.68,
        "cards_home": 0.65,
        "cards_away": 0.67,
        "dnb_home": 0.71,
        "xg": 3.21,
        "expected_corners": 8.6
      }
    }
  ],
  "hot": [
    {
      "league": "Serie A",
      "home": "FC Internazionale Milano",
      "away": "Cagliari Calcio",
      "kickoff": "17/04 18:45",
      "markets": {
        "over25": 0.57,
        "corners95": 0.63,
        "cards_home": 0.52,
        "cards_away": 0.51,
        "dnb_home": 0.7,
        "xg": 3.19,
        "expected_corners": 12.6
      }
    },
    {
      "league": "Primeira Liga",
      "home": "Rio Ave FC",
      "away": "AVS",
      "kickoff": "17/04 19:45",
      "markets": {
        "over25": 0.65,
        "corners95": 0.68,
        "cards_home": 0.65,
        "cards_away": 0.67,
        "dnb_home": 0.71,
        "xg": 3.21,
        "expected_corners": 8.6
      }
    }
  ]
}