{
  "updated_at": "28/01 21:02",
  "value": [
    {
      "league": "Campeonato Brasileiro Série A",
      "home": "EC Vitória",
      "away": "Clube do Remo",
      "kickoff": "28/01 22:00",
      "markets": {
        "over25": 0.63,
        "corners95": 0.59,
        "cards_home": 0.61,
        "cards_away": 0.61,
        "dnb_home": 0.58,
        "xg": 2.44,
        "expected_corners": 9.0
      }
    },
    {
      "league": "Campeonato Brasileiro Série A",
      "home": "Coritiba FBC",
      "away": "RB Bragantino",
      "kickoff": "28/01 22:00",
      "markets": {
        "over25": 0.71,
        "corners95": 0.59,
        "cards_home": 0.63,
        "cards_away": 0.61,
        "dnb_home": 0.6,
        "xg": 3.09,
        "expected_corners": 11.9
      }
    },
    {
      "league": "Campeonato Brasileiro Série A",
      "home": "SC Internacional",
      "away": "CA Paranaense",
      "kickoff": "28/01 22:00",
      "markets": {
        "over25": 0.65,
        "corners95": 0.6,
        "cards_home": 0.65,
        "cards_away": 0.54,
        "dnb_home": 0.59,
        "xg": 2.67,
        "expected_corners": 10.9
      }
    },
    {
      "league": "Campeonato Brasileiro Série A",
      "home": "Fluminense FC",
      "away": "Grêmio FBPA",
      "kickoff": "28/01 22:30",
      "markets": {
        "over25": 0.72,
        "corners95": 0.59,
        "cards_home": 0.58,
        "cards_away": 0.63,
        "dnb_home": 0.64,
        "xg": 2.22,
        "expected_corners": 9.4
      }
    },
    {
      "league": "Campeonato Brasileiro Série A",
      "home": "SC Corinthians Paulista",
      "away": "EC Bahia",
      "kickoff": "28/01 23:00",
      "markets": {
        "over25": 0.65,
        "corners95": 0.68,
        "cards_home": 0.55,
        "cards_away": 0.55,
        "dnb_home": 0.72,
        "xg": 2.19,
        "expected_corners": 11.2
      }
    }
  ],
  "corner": [
    {
      "league": "Campeonato Brasileiro Série A",
      "home": "CA Mineiro",
      "away": "SE Palmeiras",
      "kickoff": "28/01 22:00",
      "markets": {
        "over25": 0.56,
        "corners95": 0.63,
        "cards_home": 0.59,
        "cards_away": 0.66,
        "dnb_home": 0.58,
        "xg": 3.04,
        "expected_corners": 8.7
      }
    },
    {
      "league": "Campeonato Brasileiro Série A",
      "home": "SC Corinthians Paulista",
      "away": "EC Bahia",
      "kickoff": "28/01 23:00",
      "markets": {
        "over25": 0.65,
        "corners95": 0.68,
        "cards_home": 0.55,
        "cards_away": 0.55,
        "dnb_home": 0.72,
        "xg": 2.19,
        "expected_corners": 11.2
      }
    },
    {
      "league": "Campeonato Brasileiro Série A",
      "home": "Chapecoense AF",
      "away": "Santos FC",
      "kickoff": "28/01 23:00",
      "markets": {
        "over25": 0.6,
        "corners95": 0.62,
        "cards_home": 0.67,
        "cards_away": 0.59,
        "dnb_home": 0.61,
        "xg": 3.0,
        "expected_corners": 11.2
      }
    }
  ],
  "hot": [
    {
      "league": "Campeonato Brasileiro Série A",
      "home": "SC Corinthians Paulista",
      "away": "EC Bahia",
      "kickoff": "28/01 23:00",
      "markets": {
        "over25": 0.65,
        "corners95": 0.68,
        "cards_home": 0.55,
        "cards_away": 0.55,
        "dnb_home": 0.72,
        "xg": 2.19,
        "expected_corners": 11.2
      }
    }
  ]
}