{
  "updated_at": "20/02 04:26",
  "value": [
    {
      "league": "Serie A",
      "home": "US Sassuolo Calcio",
      "away": "Hellas Verona FC",
      "kickoff": "20/02 19:45",
      "markets": {
        "over25": 0.65,
        "corners95": 0.67,
        "cards_home": 0.64,
        "cards_away": 0.57,
        "dnb_home": 0.71,
        "xg": 3.0,
        "expected_corners": 11.0
      }
    }
  ],
  "corner": [
    {
      "league": "Eredivisie",
      "home": "Fortuna Sittard",
      "away": "SBV Excelsior",
      "kickoff": "20/02 19:00",
      "markets": {
        "over25": 0.58,
        "corners95": 0.7,
        "cards_home": 0.55,
        "cards_away": 0.67,
        "dnb_home": 0.6,
        "xg": 2.78,
        "expected_corners": 9.6
      }
    },
    {
      "league": "Serie A",
      "home": "US Sassuolo Calcio",
      "away": "Hellas Verona FC",
      "kickoff": "20/02 19:45",
      "markets": {
        "over25": 0.65,
        "corners95": 0.67,
        "cards_home": 0.64,
        "cards_away": 0.57,
        "dnb_home": 0.71,
        "xg": 3.0,
        "expected_corners": 11.0
      }
    },
    {
      "league": "Championship",
      "home": "Blackburn Rovers FC",
      "away": "Preston North End FC",
      "kickoff": "20/02 20:00",
      "markets": {
        "over25": 0.58,
        "corners95": 0.65,
        "cards_home": 0.56,
        "cards_away": 0.6,
        "dnb_home": 0.64,
        "xg": 3.11,
        "expected_corners": 10.6
      }
    },
    {
      "league": "Primera Division",
      "home": "Athletic Club",
      "away": "Elche CF",
      "kickoff": "20/02 20:00",
      "markets": {
        "over25": 0.62,
        "corners95": 0.69,
        "cards_home": 0.51,
        "cards_away": 0.66,
        "dnb_home": 0.65,
        "xg": 3.26,
        "expected_corners": 11.0
      }
    },
    {
      "league": "Primeira Liga",
      "home": "CF Estrela da Amadora",
      "away": "CD Tondela",
      "kickoff": "20/02 20:45",
      "markets": {
        "over25": 0.61,
        "corners95": 0.69,
        "cards_home": 0.66,
        "cards_away": 0.52,
        "dnb_home": 0.68,
        "xg": 2.45,
        "expected_corners": 9.5
      }
    }
  ],
  "hot": [
    {
      "league": "Serie A",
      "home": "US Sassuolo Calcio",
      "away": "Hellas Verona FC",
      "kickoff": "20/02 19:45",
      "markets": {
        "over25": 0.65,
        "corners95": 0.67,
        "cards_home": 0.64,
        "cards_away": 0.57,
        "dnb_home": 0.71,
        "xg": 3.0,
        "expected_corners": 11.0
      }
    }
  ]
}