{
  "updated_at": "19/02 23:56",
  "value": [
    {
      "league": "Copa Libertadores",
      "home": "Juventud de Las Piedras",
      "away": "Club Guaraní",
      "kickoff": "19/02 22:00",
      "markets": {
        "over25": 0.66,
        "corners95": 0.68,
        "cards_home": 0.55,
        "cards_away": 0.59,
        "dnb_home": 0.66,
        "xg": 2.3,
        "expected_corners": 9.7
      }
    }
  ],
  "corner": [
    {
      "league": "Copa Libertadores",
      "home": "Juventud de Las Piedras",
      "away": "Club Guaraní",
      "kickoff": "19/02 22:00",
      "markets": {
        "over25": 0.66,
        "corners95": 0.68,
        "cards_home": 0.55,
        "cards_away": 0.59,
        "dnb_home": 0.66,
        "xg": 2.3,
        "expected_corners": 9.7
      }
    }
  ],
  "hot": []
}