{
  "updated_at": "25/02 07:32",
  "value": [
    {
      "league": "UEFA Champions League",
      "home": "Atalanta BC",
      "away": "Borussia Dortmund",
      "kickoff": "25/02 17:45",
      "markets": {
        "over25": 0.69,
        "corners95": 0.6,
        "cards_home": 0.61,
        "cards_away": 0.67,
        "dnb_home": 0.62,
        "xg": 2.67,
        "expected_corners": 9.2
      }
    },
    {
      "league": "Championship",
      "home": "Sheffield United FC",
      "away": "Coventry City FC",
      "kickoff": "25/02 19:45",
      "markets": {
        "over25": 0.64,
        "corners95": 0.67,
        "cards_home": 0.52,
        "cards_away": 0.64,
        "dnb_home": 0.57,
        "xg": 2.56,
        "expected_corners": 8.6
      }
    },
    {
      "league": "Championship",
      "home": "Stoke City FC",
      "away": "Oxford United FC",
      "kickoff": "25/02 20:00",
      "markets": {
        "over25": 0.71,
        "corners95": 0.67,
        "cards_home": 0.61,
        "cards_away": 0.61,
        "dnb_home": 0.72,
        "xg": 3.37,
        "expected_corners": 12.3
      }
    },
    {
      "league": "Campeonato Brasileiro Série A",
      "home": "RB Bragantino",
      "away": "CA Paranaense",
      "kickoff": "25/02 22:00",
      "markets": {
        "over25": 0.65,
        "corners95": 0.6,
        "cards_home": 0.51,
        "cards_away": 0.63,
        "dnb_home": 0.58,
        "xg": 2.61,
        "expected_corners": 9.1
      }
    },
    {
      "league": "Copa Libertadores",
      "home": "EC Bahia",
      "away": "O'Higgins FC",
      "kickoff": "25/02 22:00",
      "markets": {
        "over25": 0.7,
        "corners95": 0.62,
        "cards_home": 0.66,
        "cards_away": 0.57,
        "dnb_home": 0.56,
        "xg": 2.36,
        "expected_corners": 8.7
      }
    },
    {
      "league": "Campeonato Brasileiro Série A",
      "home": "Coritiba FBC",
      "away": "São Paulo FC",
      "kickoff": "25/02 22:30",
      "markets": {
        "over25": 0.71,
        "corners95": 0.6,
        "cards_home": 0.67,
        "cards_away": 0.51,
        "dnb_home": 0.62,
        "xg": 2.46,
        "expected_corners": 12.2
      }
    },
    {
      "league": "Campeonato Brasileiro Série A",
      "home": "Cruzeiro EC",
      "away": "SC Corinthians Paulista",
      "kickoff": "25/02 23:00",
      "markets": {
        "over25": 0.66,
        "corners95": 0.67,
        "cards_home": 0.54,
        "cards_away": 0.66,
        "dnb_home": 0.67,
        "xg": 2.66,
        "expected_corners": 8.8
      }
    }
  ],
  "corner": [
    {
      "league": "Championship",
      "home": "Norwich City FC",
      "away": "Sheffield Wednesday FC",
      "kickoff": "25/02 19:45",
      "markets": {
        "over25": 0.61,
        "corners95": 0.66,
        "cards_home": 0.58,
        "cards_away": 0.54,
        "dnb_home": 0.58,
        "xg": 2.19,
        "expected_corners": 10.6
      }
    },
    {
      "league": "Championship",
      "home": "Sheffield United FC",
      "away": "Coventry City FC",
      "kickoff": "25/02 19:45",
      "markets": {
        "over25": 0.64,
        "corners95": 0.67,
        "cards_home": 0.52,
        "cards_away": 0.64,
        "dnb_home": 0.57,
        "xg": 2.56,
        "expected_corners": 8.6
      }
    },
    {
      "league": "Championship",
      "home": "Millwall FC",
      "away": "Birmingham City FC",
      "kickoff": "25/02 19:45",
      "markets": {
        "over25": 0.56,
        "corners95": 0.63,
        "cards_home": 0.68,
        "cards_away": 0.56,
        "dnb_home": 0.74,
        "xg": 2.93,
        "expected_corners": 9.1
      }
    },
    {
      "league": "UEFA Champions League",
      "home": "Paris Saint-Germain FC",
      "away": "AS Monaco FC",
      "kickoff": "25/02 20:00",
      "markets": {
        "over25": 0.56,
        "corners95": 0.61,
        "cards_home": 0.67,
        "cards_away": 0.67,
        "dnb_home": 0.71,
        "xg": 2.25,
        "expected_corners": 12.1
      }
    },
    {
      "league": "Championship",
      "home": "Stoke City FC",
      "away": "Oxford United FC",
      "kickoff": "25/02 20:00",
      "markets": {
        "over25": 0.71,
        "corners95": 0.67,
        "cards_home": 0.61,
        "cards_away": 0.61,
        "dnb_home": 0.72,
        "xg": 3.37,
        "expected_corners": 12.3
      }
    },
    {
      "league": "UEFA Champions League",
      "home": "Real Madrid CF",
      "away": "Sport Lisboa e Benfica",
      "kickoff": "25/02 20:00",
      "markets": {
        "over25": 0.57,
        "corners95": 0.68,
        "cards_home": 0.65,
        "cards_away": 0.51,
        "dnb_home": 0.71,
        "xg": 2.95,
        "expected_corners": 11.6
      }
    },
    {
      "league": "UEFA Champions League",
      "home": "Juventus FC",
      "away": "Galatasaray SK",
      "kickoff": "25/02 20:00",
      "markets": {
        "over25": 0.62,
        "corners95": 0.64,
        "cards_home": 0.53,
        "cards_away": 0.56,
        "dnb_home": 0.74,
        "xg": 2.12,
        "expected_corners": 8.8
      }
    },
    {
      "league": "Campeonato Brasileiro Série A",
      "home": "Clube do Remo",
      "away": "SC Internacional",
      "kickoff": "25/02 22:00",
      "markets": {
        "over25": 0.62,
        "corners95": 0.66,
        "cards_home": 0.52,
        "cards_away": 0.6,
        "dnb_home": 0.58,
        "xg": 2.21,
        "expected_corners": 11.2
      }
    },
    {
      "league": "Copa Libertadores",
      "home": "EC Bahia",
      "away": "O'Higgins FC",
      "kickoff": "25/02 22:00",
      "markets": {
        "over25": 0.7,
        "corners95": 0.62,
        "cards_home": 0.66,
        "cards_away": 0.57,
        "dnb_home": 0.56,
        "xg": 2.36,
        "expected_corners": 8.7
      }
    },
    {
      "league": "Campeonato Brasileiro Série A",
      "home": "Cruzeiro EC",
      "away": "SC Corinthians Paulista",
      "kickoff": "25/02 23:00",
      "markets": {
        "over25": 0.66,
        "corners95": 0.67,
        "cards_home": 0.54,
        "cards_away": 0.66,
        "dnb_home": 0.67,
        "xg": 2.66,
        "expected_corners": 8.8
      }
    }
  ],
  "hot": [
    {
      "league": "Championship",
      "home": "Millwall FC",
      "away": "Birmingham City FC",
      "kickoff": "25/02 19:45",
      "markets": {
        "over25": 0.56,
        "corners95": 0.63,
        "cards_home": 0.68,
        "cards_away": 0.56,
        "dnb_home": 0.74,
        "xg": 2.93,
        "expected_corners": 9.1
      }
    },
    {
      "league": "UEFA Champions League",
      "home": "Paris Saint-Germain FC",
      "away": "AS Monaco FC",
      "kickoff": "25/02 20:00",
      "markets": {
        "over25": 0.56,
        "corners95": 0.61,
        "cards_home": 0.67,
        "cards_away": 0.67,
        "dnb_home": 0.71,
        "xg": 2.25,
        "expected_corners": 12.1
      }
    },
    {
      "league": "Championship",
      "home": "Stoke City FC",
      "away": "Oxford United FC",
      "kickoff": "25/02 20:00",
      "markets": {
        "over25": 0.71,
        "corners95": 0.67,
        "cards_home": 0.61,
        "cards_away": 0.61,
        "dnb_home": 0.72,
        "xg": 3.37,
        "expected_corners": 12.3
      }
    },
    {
      "league": "UEFA Champions League",
      "home": "Real Madrid CF",
      "away": "Sport Lisboa e Benfica",
      "kickoff": "25/02 20:00",
      "markets": {
        "over25": 0.57,
        "corners95": 0.68,
        "cards_home": 0.65,
        "cards_away": 0.51,
        "dnb_home": 0.71,
        "xg": 2.95,
        "expected_corners": 11.6
      }
    },
    {
      "league": "UEFA Champions League",
      "home": "Juventus FC",
      "away": "Galatasaray SK",
      "kickoff": "25/02 20:00",
      "markets": {
        "over25": 0.62,
        "corners95": 0.64,
        "cards_home": 0.53,
        "cards_away": 0.56,
        "dnb_home": 0.74,
        "xg": 2.12,
        "expected_corners": 8.8
      }
    }
  ]
}