{
  "updated_at": "02/04 15:34",
  "value": [
    {
      "league": "Campeonato Brasileiro Série A",
      "home": "Chapecoense AF",
      "away": "CA Mineiro",
      "kickoff": "02/04 22:00",
      "markets": {
        "over25": 0.72,
        "corners95": 0.65,
        "cards_home": 0.55,
        "cards_away": 0.57,
        "dnb_home": 0.7,
        "xg": 3.08,
        "expected_corners": 11.4
      }
    },
    {
      "league": "Campeonato Brasileiro Série A",
      "home": "Santos FC",
      "away": "Clube do Remo",
      "kickoff": "02/04 22:00",
      "markets": {
        "over25": 0.71,
        "corners95": 0.58,
        "cards_home": 0.66,
        "cards_away": 0.6,
        "dnb_home": 0.56,
        "xg": 2.33,
        "expected_corners": 9.9
      }
    }
  ],
  "corner": [
    {
      "league": "Campeonato Brasileiro Série A",
      "home": "Chapecoense AF",
      "away": "CA Mineiro",
      "kickoff": "02/04 22:00",
      "markets": {
        "over25": 0.72,
        "corners95": 0.65,
        "cards_home": 0.55,
        "cards_away": 0.57,
        "dnb_home": 0.7,
        "xg": 3.08,
        "expected_corners": 11.4
      }
    }
  ],
  "hot": [
    {
      "league": "Campeonato Brasileiro Série A",
      "home": "Chapecoense AF",
      "away": "CA Mineiro",
      "kickoff": "02/04 22:00",
      "markets": {
        "over25": 0.72,
        "corners95": 0.65,
        "cards_home": 0.55,
        "cards_away": 0.57,
        "dnb_home": 0.7,
        "xg": 3.08,
        "expected_corners": 11.4
      }
    }
  ]
}